adjectiveanimalnumber/__init__.py
adjectiveanimalnumber/__main__.py
adjectiveanimalnumber/adjectives.py
adjectiveanimalnumber/animals.py
adjectiveanimalnumber-0.0.1.dist-info/LICENSE
adjectiveanimalnumber-0.0.1.dist-info/METADATA
adjectiveanimalnumber-0.0.1.dist-info/WHEEL
adjectiveanimalnumber-0.0.1.dist-info/entry_points.txt
adjectiveanimalnumber-0.0.1.dist-info/top_level.txt
adjectiveanimalnumber-0.0.1.dist-info/RECORD
