Metadata-Version: 2.1
Name: adjectiveanimalnumber
Version: 0.0.1
Summary: A simple package to generate random adjectives with an animal name and a random integer.
Home-page: https://github.com/pasqualedem/adjectiveanimalnumber
Author: Pasquale De Marinis
Author-email: pas.demarinis@gmail.com
License: UNKNOWN
Platform: UNKNOWN
Classifier: Programming Language :: Python :: 3
Classifier: License :: OSI Approved :: MIT License
Classifier: Operating System :: OS Independent
Requires-Python: >=3
License-File: LICENSE
